segmentation/__init__.py
segmentation/detect copy.py
segmentation/detect_good_samples.py
segmentation/export.py
segmentation/setup.py
segmentation/test.py
segmentation/train.py
segmentation/val.py
segmentation/models/__init__.py
segmentation/models/modeling.py
segmentation/models/deeplabv3/__init__.py
segmentation/models/deeplabv3/_deeplab.py
segmentation/models/deeplabv3/modeling.py
segmentation/models/deeplabv3/utils.py
segmentation/models/deeplabv3/backbone/__init__.py
segmentation/models/deeplabv3/backbone/hrnetv2.py
segmentation/models/deeplabv3/backbone/mobilenetv2.py
segmentation/models/deeplabv3/backbone/resnet.py
segmentation/src/__init__.py
segmentation/src/arguments.py
segmentation/src/coco_utils.py
segmentation/src/datasets.py
segmentation/src/losses.py
segmentation/src/presets.py
segmentation/src/transforms.py
segmentation/src/transforms_.py
segmentation/src/utils.py
segmentation/utils/__init__.py
segmentation/utils/ddp.py
segmentation/utils/logger.py
segmentation/utils/post_processing.py
yolo/__init__.py
yolo/detect.py
yolo/export.py
yolo/hubconf.py
yolo/train.py
yolo/val.py
yolo/models/__init__.py
yolo/models/common.py
yolo/models/experimental.py
yolo/models/tf.py
yolo/models/yolo.py
yolo/utils/__init__.py
yolo/utils/activations.py
yolo/utils/augmentations.py
yolo/utils/autoanchor.py
yolo/utils/autobatch.py
yolo/utils/callbacks.py
yolo/utils/datasets.py
yolo/utils/downloads.py
yolo/utils/general.py
yolo/utils/loss.py
yolo/utils/metrics.py
yolo/utils/plots.py
yolo/utils/torch_utils.py
yolo/utils/aws/__init__.py
yolo/utils/aws/resume.py
yolo/utils/loggers/__init__.py
yolo/utils/loggers/wandb/__init__.py
yolo/utils/loggers/wandb/log_dataset.py
yolo/utils/loggers/wandb/sweep.py
yolo/utils/loggers/wandb/wandb_utils.py
aiv_ml-0.0.2.dist-info/METADATA
aiv_ml-0.0.2.dist-info/WHEEL
aiv_ml-0.0.2.dist-info/top_level.txt
aiv_ml-0.0.2.dist-info/RECORD
